Metadata-Version: 2.1
Name: sentry-auth-oidc-shib
Version: 2.0.0
Summary: OpenID Connect authentication provider for Sentry (Shibboleth)
License: Apache 2.0
Author: Michael Fuchs
Author-email: michael.fuchs@hm.edu
Requires-Python: >=3.8.1
Classifier: Intended Audience :: Developers
Classifier: Intended Audience :: System Administrators
Classifier: License :: Other/Proprietary License
Classifier: Operating System :: OS Independent
Classifier: Programming Language :: Python :: 3
Classifier: Programming Language :: Python :: 3.9
Classifier: Programming Language :: Python :: 3.10
Classifier: Programming Language :: Python :: 3.11
Classifier: Programming Language :: Python :: 3.12
Classifier: Topic :: Software Development
